{
  "kind": "singleType",
  "collectionName": "global_settings",
  "info": {
    "singularName": "global-setting",
    "pluralName": "global-settings",
    "displayName": "Global Setting"
  },
  "options": {
    "draftAndPublish": true
  },
  "attributes": {
    "companyName": {
      "type": "string",
      "default": "Dayaprima"
    },
    "tagline": {
      "type": "string"
    },
    "phone": {
      "type": "string"
    },
    "whatsapp": {
      "type": "string"
    },
    "email": {
      "type": "email"
    },
    "address": {
      "type": "text"
    },
    "socialLinks": {
      "type": "component",
      "repeatable": true,
      "component": "shared.social-link"
    }
  }
}
